pytest_parametrize_suite/__init__.py
pytest_parametrize_suite/core.py
pytest_parametrize_suite/plugin.py
pytest_parametrize_suite/py.typed
pytest_parametrize_suite-23.1.2.dist-info/LICENSE
pytest_parametrize_suite-23.1.2.dist-info/WHEEL
pytest_parametrize_suite-23.1.2.dist-info/entry_points.txt
pytest_parametrize_suite-23.1.2.dist-info/METADATA
pytest_parametrize_suite-23.1.2.dist-info/RECORD
