Metadata-Version: 2.1
Name: pytest-parametrize-suite
Version: 23.1.2
Summary: A simple pytest extension for creating a named test suite.
License: GPL-3.0
Author: Sean Stewart
Author-email: sean_stewart@me.com
Requires-Python: >=3.8.1,<4.0
Classifier: Development Status :: 5 - Production/Stable
Classifier: Environment :: Plugins
Classifier: Framework :: Pytest
Classifier: Intended Audience :: Developers
Classifier: License :: OSI Approved :: GNU General Public License v3 (GPLv3)
Classifier: Programming Language :: Python :: 3
Classifier: Programming Language :: Python :: 3.9
Classifier: Programming Language :: Python :: 3.10
Classifier: Programming Language :: Python :: 3.11
Classifier: Programming Language :: Python :: 3 :: Only
Classifier: Topic :: Software Development :: Libraries
Classifier: Topic :: Software Development :: Testing
Requires-Dist: pytest
Requires-Dist: typing-extensions (>=4.4.0,<5.0.0) ; python_version < "3.10"
